judgeval/__init__.py
judgeval/cli.py
judgeval/constants.py
judgeval/env.py
judgeval/exceptions.py
judgeval/judgment_attribute_keys.py
judgeval/logger.py
judgeval/version.py
judgeval/warnings.py
judgeval/api/__init__.py
judgeval/api/api_types.py
judgeval/data/__init__.py
judgeval/data/evaluation_run.py
judgeval/data/example.py
judgeval/data/judgment_types.py
judgeval/data/result.py
judgeval/data/scorer_data.py
judgeval/data/trace.py
judgeval/data/scripts/fix_default_factory.py
judgeval/data/scripts/openapi_transform.py
judgeval/dataset/__init__.py
judgeval/evaluation/__init__.py
judgeval/integrations/langgraph/__init__.py
judgeval/integrations/openlit/__init__.py
judgeval/judges/__init__.py
judgeval/judges/base_judge.py
judgeval/judges/litellm_judge.py
judgeval/judges/together_judge.py
judgeval/judges/utils.py
judgeval/prompt/__init__.py
judgeval/scorers/__init__.py
judgeval/scorers/agent_scorer.py
judgeval/scorers/api_scorer.py
judgeval/scorers/base_scorer.py
judgeval/scorers/example_scorer.py
judgeval/scorers/exceptions.py
judgeval/scorers/score.py
judgeval/scorers/utils.py
judgeval/scorers/judgeval_scorers/__init__.py
judgeval/scorers/judgeval_scorers/api_scorers/__init__.py
judgeval/scorers/judgeval_scorers/api_scorers/answer_correctness.py
judgeval/scorers/judgeval_scorers/api_scorers/answer_relevancy.py
judgeval/scorers/judgeval_scorers/api_scorers/faithfulness.py
judgeval/scorers/judgeval_scorers/api_scorers/instruction_adherence.py
judgeval/scorers/judgeval_scorers/api_scorers/prompt_scorer.py
judgeval/tracer/__init__.py
judgeval/tracer/constants.py
judgeval/tracer/keys.py
judgeval/tracer/managers.py
judgeval/tracer/utils.py
judgeval/tracer/exporters/__init__.py
judgeval/tracer/exporters/s3.py
judgeval/tracer/exporters/store.py
judgeval/tracer/exporters/utils.py
judgeval/tracer/llm/__init__.py
judgeval/tracer/llm/config.py
judgeval/tracer/llm/constants.py
judgeval/tracer/llm/providers.py
judgeval/tracer/llm/llm_anthropic/__init__.py
judgeval-0.23.12.dist-info/METADATA
judgeval-0.23.12.dist-info/WHEEL
judgeval-0.23.12.dist-info/entry_points.txt
judgeval-0.23.12.dist-info/licenses/LICENSE.md
judgeval-0.23.12.dist-info/RECORD
