Metadata-Version: 2.4
Name: judgeval
Version: 0.23.12
Summary: The open source post-building layer for Agent Behavior Monitoring.
Project-URL: Homepage, https://github.com/JudgmentLabs/judgeval
Project-URL: Issues, https://github.com/JudgmentLabs/judgeval/issues
Author-email: Andrew Li <andrew@judgmentlabs.ai>, Alex Shan <alex@judgmentlabs.ai>, Joseph Camyre <joseph@judgmentlabs.ai>
Maintainer-email: Judgment Labs <contact@judgmentlabs.ai>
License-Expression: Apache-2.0
License-File: LICENSE.md
Classifier: Operating System :: OS Independent
Classifier: Programming Language :: Python :: 3
Requires-Python: >=3.10
Requires-Dist: boto3>=1.40.11
Requires-Dist: click<8.2.0
Requires-Dist: dotenv>=0.9.9
Requires-Dist: httpx>=0.28.1
Requires-Dist: litellm>=1.75.0
Requires-Dist: opentelemetry-exporter-otlp>=1.36.0
Requires-Dist: opentelemetry-sdk>=1.36.0
Requires-Dist: orjson>=3.9.0
Requires-Dist: typer>=0.9.0
Provides-Extra: s3
Requires-Dist: boto3>=1.40.11; extra == 's3'
Provides-Extra: trainer
Requires-Dist: fireworks-ai>=0.19.18; extra == 'trainer'
